[
  {
    "position": 1,
    "name": "Hydrogen",
    "quantity": 1,
    "email": "abc@gmail.com",
    "status": "pending",
    "transectionid": "123",
    "orderdate": "12-12-2023",
    "imageUrl": "./assets/images/bird.jpg"
  },
  {
    "position": 2,
    "name": "Helium",
    "quantity": 2,
    "email": "def@gmail.com",
    "status": "processing",
    "transectionid": "456",
    "orderdate": "11-11-2023",
    "imageUrl": "./assets/images/flower.jpg"
  },
  {
    "position": 3,
    "name": "Lithium",
    "quantity": 3,
    "email": "ghi@gmail.com",
    "status": "completed",
    "transectionid": "789",
    "orderdate": "10-10-2023",
    "imageUrl": "./assets/images/animal.jpg"
  },
  {
    "position": 4,
    "name": "Beryllium",
    "quantity": 4,
    "email": "jkl@gmail.com",
    "status": "cancelled",
    "transectionid": "101",
    "orderdate": "09-09-2023",
    "imageUrl": "./assets/images/profile.jpg"
  },
  {
    "position": 5,
    "name": "Boron",
    "quantity": 5,
    "email": "mno@gmail.com",
    "status": "pending",
    "transectionid": "202",
    "orderdate": "08-08-2023",
    "imageUrl": "./assets/images/river.jpg"
  },
  {
    "position": 6,
    "name": "Boron",
    "quantity": 5,
    "email": "mno@gmail.com",
    "status": "pending",
    "transectionid": "202",
    "orderdate": "08-08-2023",
    "imageUrl": "./assets/images/river.jpg"
  }
]
